kraken_entity_client/__init__.py
kraken_entity_client/kraken_entities_client.py
kraken_entity_client/kraken_entity_client.py
kraken_entity_client-0.0.2.dist-info/LICENSE.txt
kraken_entity_client-0.0.2.dist-info/METADATA
kraken_entity_client-0.0.2.dist-info/WHEEL
kraken_entity_client-0.0.2.dist-info/top_level.txt
kraken_entity_client-0.0.2.dist-info/RECORD
