Metadata-Version: 2.1
Name: kraken-entity-client
Version: 0.0.2
Summary: Kraken Entity Client
Home-page: https://github.com/tactik8/kraken_entity_client
Author: Tactik8
Author-email: info@tactik8.com
License: MIT
Platform: UNKNOWN
Classifier: License :: OSI Approved :: MIT License
Classifier: Programming Language :: Python :: 3
Classifier: Programming Language :: Python :: 3.8
License-File: LICENSE.txt
Requires-Dist: requests
Requires-Dist: aiohttp
Requires-Dist: numpy
